{
  "id": "brussels-convention-relating-to-the-distribution-of-programme-carrying-signals-transmitted-by-satellite-1974",
  "type": "statute",
  "title": "Brussels Convention Relating to the Distribution of Programme-Carrying Signals Transmitted by Satellite 1974",
  "title_en": "Brussels Convention Relating to the Distribution of Programme-Carrying Signals Transmitted by Satellite 1974",
  "short_name": "Brussels Convention Relating to the Distribution of Progr...",
  "status": "in_force",
  "issued_date": "1974-05-21",
  "in_force_date": "1974-05-21",
  "url": "https://www.camlawbox.com/laws/brussels-convention-relating-to-the-distribution-of-programme-carrying-signals-transmitted-by-satellite-1974",
  "provisions": [
    {
      "provision_ref": "1",
      "section": "1",
      "title": "Brussels Convention Relating to the Distribution of Programme-Carrying Signals Transmitted by Satellite 1974",
      "content": "Brussels Convention Relating to the Distribution of Programme-Carrying Signals Transmitted by Satellite 1974. Full text requires access to camlawbox.com. Date: 1974-05-21. Category: other."
    }
  ],
  "definitions": []
}