{
  "id": "collection-tax-on-rental-of-house-and-land-notification-2019",
  "type": "statute",
  "title": "Collection Tax on Rental of House and Land Notification 2019",
  "title_en": "Collection Tax on Rental of House and Land Notification 2019",
  "short_name": "Collection Tax on Rental of House and Land Notification 2019",
  "status": "in_force",
  "issued_date": "2019-09-03",
  "in_force_date": "2019-09-03",
  "url": "https://www.camlawbox.com/laws/collection-tax-on-rental-of-house-and-land-notification-2019",
  "provisions": [
    {
      "provision_ref": "1",
      "section": "1",
      "title": "Collection Tax on Rental of House and Land Notification 2019",
      "content": "Collection Tax on Rental of House and Land Notification 2019. Full text requires access to camlawbox.com. Date: 2019-09-03. Category: notification."
    }
  ],
  "definitions": []
}