{
  "id": "corporate-governance-for-listed-companies-prakas-2010-repealed",
  "type": "statute",
  "title": "Corporate Governance for Listed Companies Prakas 2010 (Repealed)",
  "title_en": "Corporate Governance for Listed Companies Prakas 2010 (Repealed)",
  "short_name": "Corporate Governance for Listed Companies Prakas 2010 (Re...",
  "status": "in_force",
  "issued_date": "2010-01-15",
  "in_force_date": "2010-01-15",
  "url": "https://www.camlawbox.com/laws/corporate-governance-for-listed-companies-prakas-2010-repealed",
  "provisions": [
    {
      "provision_ref": "1",
      "section": "1",
      "title": "Corporate Governance for Listed Companies Prakas 2010 (Repealed)",
      "content": "Corporate Governance for Listed Companies Prakas 2010 (Repealed). Full text requires access to camlawbox.com. Date: 2010-01-15. Category: prakas."
    }
  ],
  "definitions": []
}