{
  "id": "determination-of-criteria-for-types-and-levels-of-disability-inter-ministerial-prakas-2011",
  "type": "statute",
  "title": "Determination of Criteria for Types and Levels of Disability Inter-ministerial Prakas 2011",
  "title_en": "Determination of Criteria for Types and Levels of Disability Inter-ministerial Prakas 2011",
  "short_name": "Determination of Criteria for Types and Levels of Disabil...",
  "status": "in_force",
  "issued_date": "2011-11-22",
  "in_force_date": "2011-11-22",
  "url": "https://www.camlawbox.com/laws/determination-of-criteria-for-types-and-levels-of-disability-inter-ministerial-prakas-2011",
  "provisions": [
    {
      "provision_ref": "1",
      "section": "1",
      "title": "Determination of Criteria for Types and Levels of Disability Inter-ministerial Prakas 2011",
      "content": "Determination of Criteria for Types and Levels of Disability Inter-ministerial Prakas 2011. Full text requires access to camlawbox.com. Date: 2011-11-22. Category: prakas."
    }
  ],
  "definitions": []
}