{
  "id": "economic-land-concessions-sub-decree-2005",
  "type": "statute",
  "title": "Economic Land Concessions Sub-Decree 2005",
  "title_en": "Economic Land Concessions Sub-Decree 2005",
  "short_name": "Economic Land Concessions Sub-Decree 2005",
  "status": "in_force",
  "issued_date": "2005-12-27",
  "in_force_date": "2005-12-27",
  "url": "https://www.camlawbox.com/laws/economic-land-concessions-sub-decree-2005",
  "provisions": [
    {
      "provision_ref": "1",
      "section": "1",
      "title": "Economic Land Concessions Sub-Decree 2005",
      "content": "Economic Land Concessions Sub-Decree 2005. Full text requires access to camlawbox.com. Date: 2005-12-27. Category: sub_decree."
    }
  ],
  "definitions": []
}