{
  "id": "establishment-of-technical-group-for-cambodian-halal-prakas-2016",
  "type": "statute",
  "title": "Establishment of Technical Group for Cambodian Halal Prakas 2016",
  "title_en": "Establishment of Technical Group for Cambodian Halal Prakas 2016",
  "short_name": "Establishment of Technical Group for Cambodian Halal Prak...",
  "status": "in_force",
  "issued_date": "2016-10-20",
  "in_force_date": "2016-10-20",
  "url": "https://www.camlawbox.com/laws/establishment-of-technical-group-for-cambodian-halal-prakas-2016",
  "provisions": [
    {
      "provision_ref": "1",
      "section": "1",
      "title": "Establishment of Technical Group for Cambodian Halal Prakas 2016",
      "content": "Establishment of Technical Group for Cambodian Halal Prakas 2016. Full text requires access to camlawbox.com. Date: 2016-10-20. Category: prakas."
    }
  ],
  "definitions": []
}