{
  "id": "establishment-of-the-rural-development-bank-sub-decree-1998",
  "type": "statute",
  "title": "Establishment of the Rural Development Bank Sub-Decree 1998",
  "title_en": "Establishment of the Rural Development Bank Sub-Decree 1998",
  "short_name": "Establishment of the Rural Development Bank Sub-Decree 1998",
  "status": "in_force",
  "issued_date": "1998-01-22",
  "in_force_date": "1998-01-22",
  "url": "https://www.camlawbox.com/laws/establishment-of-the-rural-development-bank-sub-decree-1998",
  "provisions": [
    {
      "provision_ref": "1",
      "section": "1",
      "title": "Establishment of the Rural Development Bank Sub-Decree 1998",
      "content": "Establishment of the Rural Development Bank Sub-Decree 1998. Full text requires access to camlawbox.com. Date: 1998-01-22. Category: sub_decree."
    }
  ],
  "definitions": []
}