{
  "id": "ethic-and-code-of-conduct-for-mediator-of-national-authority-for-alternative-dispute-resolution-nadr-decision-2024",
  "type": "statute",
  "title": "Ethic and Code of Conduct for Mediator of National Authority for Alternative Dispute Resolution (NADR) Decision 2024",
  "title_en": "Ethic and Code of Conduct for Mediator of National Authority for Alternative Dispute Resolution (NADR) Decision 2024",
  "short_name": "Ethic and Code of Conduct for Mediator of National Author...",
  "status": "in_force",
  "issued_date": "2024-03-29",
  "in_force_date": "2024-03-29",
  "url": "https://www.camlawbox.com/laws/ethic-and-code-of-conduct-for-mediator-of-national-authority-for-alternative-dispute-resolution-nadr-decision-2024",
  "provisions": [
    {
      "provision_ref": "1",
      "section": "1",
      "title": "Ethic and Code of Conduct for Mediator of National Authority for Alternative Dispute Resolution (NADR) Decision 2024",
      "content": "Ethic and Code of Conduct for Mediator of National Authority for Alternative Dispute Resolution (NADR) Decision 2024. Full text requires access to camlawbox.com. Date: 2024-03-29. Category: act."
    }
  ],
  "definitions": []
}