{
  "id": "exemption-of-minimum-tax-for-self-assessment-taxpayer-press-release-2019",
  "type": "statute",
  "title": "Exemption of Minimum Tax for Self-Assessment Taxpayer Press Release 2019",
  "title_en": "Exemption of Minimum Tax for Self-Assessment Taxpayer Press Release 2019",
  "short_name": "Exemption of Minimum Tax for Self-Assessment Taxpayer Pre...",
  "status": "in_force",
  "issued_date": "2019-05-29",
  "in_force_date": "2019-05-29",
  "url": "https://www.camlawbox.com/laws/exemption-of-minimum-tax-for-self-assessment-taxpayer-press-release-2019",
  "provisions": [
    {
      "provision_ref": "1",
      "section": "1",
      "title": "Exemption of Minimum Tax for Self-Assessment Taxpayer Press Release 2019",
      "content": "Exemption of Minimum Tax for Self-Assessment Taxpayer Press Release 2019. Full text requires access to camlawbox.com. Date: 2019-05-29. Category: other."
    }
  ],
  "definitions": []
}