{
  "id": "financial-management-for-year-2010-law-2009",
  "type": "statute",
  "title": "Financial Management For Year 2010 Law 2009",
  "title_en": "Financial Management For Year 2010 Law 2009",
  "short_name": "Financial Management For Year 2010 Law 2009",
  "status": "in_force",
  "issued_date": "2009-12-16",
  "in_force_date": "2009-12-16",
  "url": "https://www.camlawbox.com/laws/financial-management-for-year-2010-law-2009",
  "provisions": [
    {
      "provision_ref": "1",
      "section": "1",
      "title": "Financial Management For Year 2010 Law 2009",
      "content": "Financial Management For Year 2010 Law 2009. Full text requires access to camlawbox.com. Date: 2009-12-16. Category: act."
    }
  ],
  "definitions": []
}