{
  "id": "fisheries-law-2006-repealed",
  "type": "statute",
  "title": "Fisheries Law 2006 (Repealed)",
  "title_en": "Fisheries Law 2006 (Repealed)",
  "short_name": "Fisheries Law 2006 (Repealed)",
  "status": "in_force",
  "issued_date": "2006-05-21",
  "in_force_date": "2006-05-21",
  "url": "https://www.camlawbox.com/laws/fisheries-law-2006-repealed",
  "provisions": [
    {
      "provision_ref": "1",
      "section": "1",
      "title": "Fisheries Law 2006 (Repealed)",
      "content": "Fisheries Law 2006 (Repealed). Full text requires access to camlawbox.com. Date: 2006-05-21. Category: act."
    }
  ],
  "definitions": []
}