{
  "id": "import-management-of-non-commercial-circular-2005",
  "type": "statute",
  "title": "Import Management of Non-Commercial Circular 2005",
  "title_en": "Import Management of Non-Commercial Circular 2005",
  "short_name": "Import Management of Non-Commercial Circular 2005",
  "status": "in_force",
  "issued_date": "2005-12-01",
  "in_force_date": "2005-12-01",
  "url": "https://www.camlawbox.com/laws/import-management-of-non-commercial-circular-2005",
  "provisions": [
    {
      "provision_ref": "1",
      "section": "1",
      "title": "Import Management of Non-Commercial Circular 2005",
      "content": "Import Management of Non-Commercial Circular 2005. Full text requires access to camlawbox.com. Date: 2005-12-01. Category: regulation."
    }
  ],
  "definitions": []
}