{
  "id": "maintenance-of-reserve-requirement-against-banking-and-financial-institutions-deposits-and-borrowings-prakas-2023",
  "type": "statute",
  "title": "Maintenance of Reserve Requirement against Banking and Financial Institutions' Deposits and Borrowings Prakas 2023",
  "title_en": "Maintenance of Reserve Requirement against Banking and Financial Institutions' Deposits and Borrowings Prakas 2023",
  "short_name": "Maintenance of Reserve Requirement against Banking and Fi...",
  "status": "in_force",
  "issued_date": "2023-01-09",
  "in_force_date": "2023-01-09",
  "url": "https://www.camlawbox.com/laws/maintenance-of-reserve-requirement-against-banking-and-financial-institutions-deposits-and-borrowings-prakas-2023",
  "provisions": [
    {
      "provision_ref": "1",
      "section": "1",
      "title": "Maintenance of Reserve Requirement against Banking and Financial Institutions' Deposits and Borrowings Prakas 2023",
      "content": "Maintenance of Reserve Requirement against Banking and Financial Institutions' Deposits and Borrowings Prakas 2023. Full text requires access to camlawbox.com. Date: 2023-01-09. Category: prakas."
    }
  ],
  "definitions": []
}