{
  "id": "management-of-health-center-located-inside-or-nearby-referral-hospital-prakas-2003",
  "type": "statute",
  "title": "Management of Health Center Located inside or Nearby Referral Hospital Prakas 2003",
  "title_en": "Management of Health Center Located inside or Nearby Referral Hospital Prakas 2003",
  "short_name": "Management of Health Center Located inside or Nearby Refe...",
  "status": "in_force",
  "issued_date": "2003-08-22",
  "in_force_date": "2003-08-22",
  "url": "https://www.camlawbox.com/laws/management-of-health-center-located-inside-or-nearby-referral-hospital-prakas-2003",
  "provisions": [
    {
      "provision_ref": "1",
      "section": "1",
      "title": "Management of Health Center Located inside or Nearby Referral Hospital Prakas 2003",
      "content": "Management of Health Center Located inside or Nearby Referral Hospital Prakas 2003. Full text requires access to camlawbox.com. Date: 2003-08-22. Category: prakas."
    }
  ],
  "definitions": []
}