{
  "id": "mechanism-on-instruction-in-trading-securities-principle-guideline-2014",
  "type": "statute",
  "title": "Mechanism on Instruction in Trading Securities Principle Guideline 2014",
  "title_en": "Mechanism on Instruction in Trading Securities Principle Guideline 2014",
  "short_name": "Mechanism on Instruction in Trading Securities Principle ...",
  "status": "in_force",
  "issued_date": "2014-03-17",
  "in_force_date": "2014-03-17",
  "url": "https://www.camlawbox.com/laws/mechanism-on-instruction-in-trading-securities-principle-guideline-2014",
  "provisions": [
    {
      "provision_ref": "1",
      "section": "1",
      "title": "Mechanism on Instruction in Trading Securities Principle Guideline 2014",
      "content": "Mechanism on Instruction in Trading Securities Principle Guideline 2014. Full text requires access to camlawbox.com. Date: 2014-03-17. Category: instruction."
    }
  ],
  "definitions": []
}