{
  "id": "modality-and-procedure-of-trust-inspection-prakas-2022",
  "type": "statute",
  "title": "Modality and Procedure of Trust Inspection Prakas 2022",
  "title_en": "Modality and Procedure of Trust Inspection Prakas 2022",
  "short_name": "Modality and Procedure of Trust Inspection Prakas 2022",
  "status": "in_force",
  "issued_date": "2022-12-03",
  "in_force_date": "2022-12-03",
  "url": "https://www.camlawbox.com/laws/modality-and-procedure-of-trust-inspection-prakas-2022",
  "provisions": [
    {
      "provision_ref": "1",
      "section": "1",
      "title": "Modality and Procedure of Trust Inspection Prakas 2022",
      "content": "Modality and Procedure of Trust Inspection Prakas 2022. Full text requires access to camlawbox.com. Date: 2022-12-03. Category: prakas."
    }
  ],
  "definitions": []
}