{
  "id": "opening-of-salary-to-workers-2-times-per-month-press-release-2019",
  "type": "statute",
  "title": "Opening of Salary to Workers 2 Times per Month Press Release 2019",
  "title_en": "Opening of Salary to Workers 2 Times per Month Press Release 2019",
  "short_name": "Opening of Salary to Workers 2 Times per Month Press Rele...",
  "status": "in_force",
  "issued_date": "2019-01-16",
  "in_force_date": "2019-01-16",
  "url": "https://www.camlawbox.com/laws/opening-of-salary-to-workers-2-times-per-month-press-release-2019",
  "provisions": [
    {
      "provision_ref": "1",
      "section": "1",
      "title": "Opening of Salary to Workers 2 Times per Month Press Release 2019",
      "content": "Opening of Salary to Workers 2 Times per Month Press Release 2019. Full text requires access to camlawbox.com. Date: 2019-01-16. Category: other."
    }
  ],
  "definitions": []
}