{
  "id": "postal-sector-development-policy-2022-2030",
  "type": "statute",
  "title": "Postal Sector Development Policy 2022-2030",
  "title_en": "Postal Sector Development Policy 2022-2030",
  "short_name": "Postal Sector Development Policy 2022-2030",
  "status": "in_force",
  "issued_date": "2022-09-09",
  "in_force_date": "2022-09-09",
  "url": "https://www.camlawbox.com/laws/postal-sector-development-policy-2022-2030",
  "provisions": [
    {
      "provision_ref": "1",
      "section": "1",
      "title": "Postal Sector Development Policy 2022-2030",
      "content": "Postal Sector Development Policy 2022-2030. Full text requires access to camlawbox.com. Date: 2022-09-09. Category: other."
    }
  ],
  "definitions": []
}