{
  "id": "procedure-of-cash-settlement-in-the-securities-market-guidelines-2012",
  "type": "statute",
  "title": "Procedure of Cash Settlement in the Securities Market Guidelines 2012",
  "title_en": "Procedure of Cash Settlement in the Securities Market Guidelines 2012",
  "short_name": "Procedure of Cash Settlement in the Securities Market Gui...",
  "status": "in_force",
  "issued_date": "2012-02-14",
  "in_force_date": "2012-02-14",
  "url": "https://www.camlawbox.com/laws/procedure-of-cash-settlement-in-the-securities-market-guidelines-2012",
  "provisions": [
    {
      "provision_ref": "1",
      "section": "1",
      "title": "Procedure of Cash Settlement in the Securities Market Guidelines 2012",
      "content": "Procedure of Cash Settlement in the Securities Market Guidelines 2012. Full text requires access to camlawbox.com. Date: 2012-02-14. Category: other."
    }
  ],
  "definitions": []
}