{
  "id": "procedure-for-tax-audit-for-tax-official-and-tax-payer-guideline-2024",
  "type": "statute",
  "title": "Procedure for Tax Audit for Tax Official and Tax Payer Guideline 2024",
  "title_en": "Procedure for Tax Audit for Tax Official and Tax Payer Guideline 2024",
  "short_name": "Procedure for Tax Audit for Tax Official and Tax Payer Gu...",
  "status": "in_force",
  "issued_date": "2024-04-09",
  "in_force_date": "2024-04-09",
  "url": "https://www.camlawbox.com/laws/procedure-for-tax-audit-for-tax-official-and-tax-payer-guideline-2024",
  "provisions": [
    {
      "provision_ref": "1",
      "section": "1",
      "title": "Procedure for Tax Audit for Tax Official and Tax Payer Guideline 2024",
      "content": "Procedure for Tax Audit for Tax Official and Tax Payer Guideline 2024. Full text requires access to camlawbox.com. Date: 2024-04-09. Category: other."
    }
  ],
  "definitions": []
}