{
  "id": "rejecting-thailand-s-false-allegation-on-ceasefire-violation-statement-2025",
  "type": "statute",
  "title": "Rejecting Thailand's False Allegation on Ceasefire Violation Statement 2025",
  "title_en": "Rejecting Thailand's False Allegation on Ceasefire Violation Statement 2025",
  "short_name": "Rejecting Thailand's False Allegation on Ceasefire Violat...",
  "status": "in_force",
  "issued_date": "2025-07-30",
  "in_force_date": "2025-07-30",
  "url": "https://www.camlawbox.com/laws/rejecting-thailand-s-false-allegation-on-ceasefire-violation-statement-2025",
  "provisions": [
    {
      "provision_ref": "1",
      "section": "1",
      "title": "Rejecting Thailand's False Allegation on Ceasefire Violation Statement 2025",
      "content": "Rejecting Thailand's False Allegation on Ceasefire Violation Statement 2025. Full text requires access to camlawbox.com. Date: 2025-07-30. Category: other."
    }
  ],
  "definitions": []
}