{
  "id": "reminding-on-the-implementation-of-law-on-the-management-of-health-profession-letter-2019",
  "type": "statute",
  "title": "Reminding on the Implementation of Law on the Management of Health Profession Letter 2019",
  "title_en": "Reminding on the Implementation of Law on the Management of Health Profession Letter 2019",
  "short_name": "Reminding on the Implementation of Law on the Management ...",
  "status": "in_force",
  "issued_date": "2019-09-04",
  "in_force_date": "2019-09-04",
  "url": "https://www.camlawbox.com/laws/reminding-on-the-implementation-of-law-on-the-management-of-health-profession-letter-2019",
  "provisions": [
    {
      "provision_ref": "1",
      "section": "1",
      "title": "Reminding on the Implementation of Law on the Management of Health Profession Letter 2019",
      "content": "Reminding on the Implementation of Law on the Management of Health Profession Letter 2019. Full text requires access to camlawbox.com. Date: 2019-09-04. Category: act."
    }
  ],
  "definitions": []
}