{
  "id": "royal-gazette-no-32-year-1996",
  "type": "statute",
  "title": "Royal Gazette No. 32 Year 1996",
  "title_en": "Royal Gazette No. 32 Year 1996",
  "short_name": "Royal Gazette No. 32 Year 1996",
  "status": "in_force",
  "issued_date": "1996-08-31",
  "in_force_date": "1996-08-31",
  "url": "https://www.camlawbox.com/laws/royal-gazette-no-32-year-1996",
  "provisions": [
    {
      "provision_ref": "1",
      "section": "1",
      "title": "Royal Gazette No. 32 Year 1996",
      "content": "Royal Gazette No. 32 Year 1996. Full text requires access to camlawbox.com. Date: 1996-08-31. Category: other."
    }
  ],
  "definitions": []
}