{
  "id": "second-reminding-payment-of-immovable-property-tax-for-year-2019-notification-2019",
  "type": "statute",
  "title": "Second Reminding Payment of Immovable Property Tax For Year 2019 Notification 2019",
  "title_en": "Second Reminding Payment of Immovable Property Tax For Year 2019 Notification 2019",
  "short_name": "Second Reminding Payment of Immovable Property Tax For Ye...",
  "status": "in_force",
  "issued_date": "2019-08-21",
  "in_force_date": "2019-08-21",
  "url": "https://www.camlawbox.com/laws/second-reminding-payment-of-immovable-property-tax-for-year-2019-notification-2019",
  "provisions": [
    {
      "provision_ref": "1",
      "section": "1",
      "title": "Second Reminding Payment of Immovable Property Tax For Year 2019 Notification 2019",
      "content": "Second Reminding Payment of Immovable Property Tax For Year 2019 Notification 2019. Full text requires access to camlawbox.com. Date: 2019-08-21. Category: notification."
    }
  ],
  "definitions": []
}