{
  "id": "the-activities-of-association-non-governmental-organizations-and-local-communities-letter-2018",
  "type": "statute",
  "title": "The Activities of Association, Non-governmental Organizations and Local Communities Letter 2018",
  "title_en": "The Activities of Association, Non-governmental Organizations and Local Communities Letter 2018",
  "short_name": "The Activities of Association, Non-governmental Organizat...",
  "status": "in_force",
  "issued_date": "2018-11-27",
  "in_force_date": "2018-11-27",
  "url": "https://www.camlawbox.com/laws/the-activities-of-association-non-governmental-organizations-and-local-communities-letter-2018",
  "provisions": [
    {
      "provision_ref": "1",
      "section": "1",
      "title": "The Activities of Association, Non-governmental Organizations and Local Communities Letter 2018",
      "content": "The Activities of Association, Non-governmental Organizations and Local Communities Letter 2018. Full text requires access to camlawbox.com. Date: 2018-11-27. Category: other."
    }
  ],
  "definitions": []
}