{
  "id": "the-form-of-the-certificate-of-adoption-prakas-2008",
  "type": "statute",
  "title": "The Form of the Certificate of Adoption Prakas 2008",
  "title_en": "The Form of the Certificate of Adoption Prakas 2008",
  "short_name": "The Form of the Certificate of Adoption Prakas 2008",
  "status": "in_force",
  "issued_date": "2008-12-16",
  "in_force_date": "2008-12-16",
  "url": "https://www.camlawbox.com/laws/the-form-of-the-certificate-of-adoption-prakas-2008",
  "provisions": [
    {
      "provision_ref": "1",
      "section": "1",
      "title": "The Form of the Certificate of Adoption Prakas 2008",
      "content": "The Form of the Certificate of Adoption Prakas 2008. Full text requires access to camlawbox.com. Date: 2008-12-16. Category: prakas."
    }
  ],
  "definitions": []
}