{
  "id": "use-of-the-company-business-name-on-documents-logos-for-public-display-or-advertising-inter-ministerial-prakas-2019",
  "type": "statute",
  "title": "Use of the Company/Business Name on Documents, Logos for Public Display or Advertising Inter-Ministerial Prakas 2019",
  "title_en": "Use of the Company/Business Name on Documents, Logos for Public Display or Advertising Inter-Ministerial Prakas 2019",
  "short_name": "Use of the Company/Business Name on Documents, Logos for ...",
  "status": "in_force",
  "issued_date": "2019-09-11",
  "in_force_date": "2019-09-11",
  "url": "https://www.camlawbox.com/laws/use-of-the-company-business-name-on-documents-logos-for-public-display-or-advertising-inter-ministerial-prakas-2019",
  "provisions": [
    {
      "provision_ref": "1",
      "section": "1",
      "title": "Use of the Company/Business Name on Documents, Logos for Public Display or Advertising Inter-Ministerial Prakas 2019",
      "content": "Use of the Company/Business Name on Documents, Logos for Public Display or Advertising Inter-Ministerial Prakas 2019. Full text requires access to camlawbox.com. Date: 2019-09-11. Category: prakas."
    }
  ],
  "definitions": []
}