{
  "id": "use-of-receipt-of-filing-application-and-fee-for-certificate-and-work-permit-of-foreign-employees-prakas-2014",
  "type": "statute",
  "title": "Use of Receipt of Filing Application and Fee for Certificate and Work Permit of Foreign Employees Prakas 2014",
  "title_en": "Use of Receipt of Filing Application and Fee for Certificate and Work Permit of Foreign Employees Prakas 2014",
  "short_name": "Use of Receipt of Filing Application and Fee for Certific...",
  "status": "in_force",
  "issued_date": "2014-08-20",
  "in_force_date": "2014-08-20",
  "url": "https://www.camlawbox.com/laws/use-of-receipt-of-filing-application-and-fee-for-certificate-and-work-permit-of-foreign-employees-prakas-2014",
  "provisions": [
    {
      "provision_ref": "1",
      "section": "1",
      "title": "Use of Receipt of Filing Application and Fee for Certificate and Work Permit of Foreign Employees Prakas 2014",
      "content": "Use of Receipt of Filing Application and Fee for Certificate and Work Permit of Foreign Employees Prakas 2014. Full text requires access to camlawbox.com. Date: 2014-08-20. Category: prakas."
    }
  ],
  "definitions": []
}